kubernetes/__init__.py
kubernetes/client/__init__.py
kubernetes/client/api_client.py
kubernetes/client/configuration.py
kubernetes/client/exceptions.py
kubernetes/client/rest.py
kubernetes/client/api/__init__.py
kubernetes/client/api/admissionregistration_api.py
kubernetes/client/api/admissionregistration_v1_api.py
kubernetes/client/api/admissionregistration_v1beta1_api.py
kubernetes/client/api/apiextensions_api.py
kubernetes/client/api/apiextensions_v1_api.py
kubernetes/client/api/apiextensions_v1beta1_api.py
kubernetes/client/api/apiregistration_api.py
kubernetes/client/api/apiregistration_v1_api.py
kubernetes/client/api/apiregistration_v1beta1_api.py
kubernetes/client/api/apis_api.py
kubernetes/client/api/apps_api.py
kubernetes/client/api/apps_v1_api.py
kubernetes/client/api/authentication_api.py
kubernetes/client/api/authentication_v1_api.py
kubernetes/client/api/authentication_v1beta1_api.py
kubernetes/client/api/authorization_api.py
kubernetes/client/api/authorization_v1_api.py
kubernetes/client/api/authorization_v1beta1_api.py
kubernetes/client/api/autoscaling_api.py
kubernetes/client/api/autoscaling_v1_api.py
kubernetes/client/api/autoscaling_v2beta1_api.py
kubernetes/client/api/autoscaling_v2beta2_api.py
kubernetes/client/api/batch_api.py
kubernetes/client/api/batch_v1_api.py
kubernetes/client/api/batch_v1beta1_api.py
kubernetes/client/api/certificates_api.py
kubernetes/client/api/certificates_v1_api.py
kubernetes/client/api/certificates_v1beta1_api.py
kubernetes/client/api/coordination_api.py
kubernetes/client/api/coordination_v1_api.py
kubernetes/client/api/coordination_v1beta1_api.py
kubernetes/client/api/core_api.py
kubernetes/client/api/core_v1_api.py
kubernetes/client/api/custom_objects_api.py
kubernetes/client/api/discovery_api.py
kubernetes/client/api/discovery_v1_api.py
kubernetes/client/api/discovery_v1beta1_api.py
kubernetes/client/api/events_api.py
kubernetes/client/api/events_v1_api.py
kubernetes/client/api/events_v1beta1_api.py
grdp_cli_kubernetes-1.0.2.dist-info/LICENSE
grdp_cli_kubernetes-1.0.2.dist-info/METADATA
grdp_cli_kubernetes-1.0.2.dist-info/WHEEL
grdp_cli_kubernetes-1.0.2.dist-info/top_level.txt
grdp_cli_kubernetes-1.0.2.dist-info/RECORD
